{"medLZse5cfpGEQen2VFrpg==":"albumasymmetry-1500x1500.jpg","kTZ1u3PB4/KH8iLGNW1VwA==":"screen%20shot%202018-12-19%20at%201.24.24%20pm-2000x1439.png","2O9e1zoeGx9ulfmxmXMfMw==":"screen%20shot%202019-04-29%20at%2012.57.36%20pm-1478x2070.png","WWi43Ab4aU7YkBEIxzV8LQ==":"screen%20shot%202019-05-17%20at%2012.33.18%20pm-596x996.png","/io4lI9fTt6eXiWrAzCv4A==":"screen%20shot%202019-05-17%20at%2012.35.00%20pm-960x1368.png","TIEdhFAvIC9im0Dcyl+C+g==":"screen%20shot%202019-05-03%20at%2012.41.27%20pm-760x752.png","oxCyKTcGrcKg1/sWIg/OMA==":"screen%20shot%202019-05-17%20at%2012.33.50%20pm-814x1268.png","fAaEoRi4sKzNfikxYwdLNw==":"screen%20shot%202019-05-17%20at%201.13.06%20pm-988x1390.png","QkgEDMYHs6hgFK1eiXaXlA==":"screen%20shot%202019-05-09%20at%2012.49.51%20pm-700x504.png","FuGy0EY7p5/OhAHOHSgmBw==":"screen%20shot%202019-05-21%20at%201.07.39%20pm-1000x1400.png","wHqRbbIKPBUZKHzkUiVraQ==":"screenshot_20190521-132247_instagram-614x800.jpg","pIX6vj6R9bR2YqMqFe/g4w==":"screenshot_20190521-132254_instagram-585x770.jpg","sriDlAei5Xizs9YiIspKLw==":"screenshot_20190521-132258_instagram-534x699.jpg","E3PFDOc1aphKoQqk2o4anA==":"snapchat-833255392-720x1280.jpg","UB0XgHtIgcPm3dWl1O1Uhg==":"snapchat-833255392-192x341.jpg","+Qrl9w6D+M/fTvLHr2OnqQ==":"screen%20shot%202019-05-17%20at%2012.35.00%20pm-108x154.png"}